[
    {
        "url": "/assets/01-ស្រអែមផល្លា.wav",
        "title": "C:\\Users\\Admin\\Source\\repos\\angularAudio\\angularAudio\\public\\assets\\01-ស្រអែមផល្លា.wav"
    },
    {
        "url": "/assets/02-ស្ដាយក្លិនឆោមឆាយ.wav",
        "title": "C:\\Users\\Admin\\Source\\repos\\angularAudio\\angularAudio\\public\\assets\\02-ស្ដាយក្លិនឆោមឆាយ.wav"
    },
    {
        "url": "/assets/03-ស្រីលាវតូច.wav",
        "title": "C:\\Users\\Admin\\Source\\repos\\angularAudio\\angularAudio\\public\\assets\\03-ស្រីលាវតូច.wav"
    },
    {
        "url": "/assets/04-អាគោកខ្នាយវែង.wav",
        "title": "C:\\Users\\Admin\\Source\\repos\\angularAudio\\angularAudio\\public\\assets\\04-អាគោកខ្នាយវែង.wav"
    },
    {
        "url": "/assets/05-ឱសត្វជីងចក់.wav",
        "title": "C:\\Users\\Admin\\Source\\repos\\angularAudio\\angularAudio\\public\\assets\\05-ឱសត្វជីងចក់.wav"
    },
    {
        "url": "/assets/06-ចោលអូនម្ដេចបាន.wav",
        "title": "C:\\Users\\Admin\\Source\\repos\\angularAudio\\angularAudio\\public\\assets\\06-ចោលអូនម្ដេចបាន.wav"
    },
    {
        "url": "/assets/07-ចម្រៀងអ្នកលក់ផ្កា.wav",
        "title": "C:\\Users\\Admin\\Source\\repos\\angularAudio\\angularAudio\\public\\assets\\07-ចម្រៀងអ្នកលក់ផ្កា.wav"
    },
    {
        "url": "/assets/08-ស្ដាយឆោម.wav",
        "title": "C:\\Users\\Admin\\Source\\repos\\angularAudio\\angularAudio\\public\\assets\\08-ស្ដាយឆោម.wav"
    },
    {
        "url": "/assets/09-ច្រូចទឹកចោលទៅ.wav",
        "title": "C:\\Users\\Admin\\Source\\repos\\angularAudio\\angularAudio\\public\\assets\\09-ច្រូចទឹកចោលទៅ.wav"
    },
    {
        "url": "/assets/10-អូនមិនប្រកែក.wav",
        "title": "C:\\Users\\Admin\\Source\\repos\\angularAudio\\angularAudio\\public\\assets\\10-អូនមិនប្រកែក.wav"
    },
    {
        "url": "/assets/11-តូចចិត្តព្រោះស្នេហ៍.wav",
        "title": "C:\\Users\\Admin\\Source\\repos\\angularAudio\\angularAudio\\public\\assets\\11-តូចចិត្តព្រោះស្នេហ៍.wav"
    },
    {
        "url": "/assets/12-លេងស្ម័គ្រលែងជឿ.wav",
        "title": "C:\\Users\\Admin\\Source\\repos\\angularAudio\\angularAudio\\public\\assets\\12-លេងស្ម័គ្រលែងជឿ.wav"
    },
    {
        "url": "/assets/13-ភ័យអ្វីម្លេះទេ.wav",
        "title": "C:\\Users\\Admin\\Source\\repos\\angularAudio\\angularAudio\\public\\assets\\13-ភ័យអ្វីម្លេះទេ.wav"
    },
    {
        "url": "/assets/14-ផ្ទះផ្សារប្រាំខ្នង.wav",
        "title": "C:\\Users\\Admin\\Source\\repos\\angularAudio\\angularAudio\\public\\assets\\14-ផ្ទះផ្សារប្រាំខ្នង.wav"
    }
]